[
    {
        "image": null,
        "quiz": "Durante la marcia, il casco deve essere sempre correttamente allacciato",
        "ans": true
    },
    {
        "image": null,
        "quiz": "Il casco conserva invariate le sue caratteristiche protettive per periodi lunghissimi, di oltre venti anni",
        "ans": false
    },
    {
        "image": null,
        "quiz": "Il casco deve essere di taglia corretta",
        "ans": true
    },
    {
        "image": null,
        "quiz": "Il casco deve essere periodicamente pulito con benzina o acquaragia per sgrassarlo ed eliminare resti di insetti",
        "ans": false
    },
    {
        "image": null,
        "quiz": "Il casco deve essere sostituito dopo che abbia subito un forte urto, anche se non mostra deformazioni sulla calotta esterna",
        "ans": true
    },
    {
        "image": null,
        "quiz": "Il casco \u00e8 obbligatorio per i conducenti di ciclomotori a due ruote, solo se minorenni",
        "ans": false
    },
    {
        "image": null,
        "quiz": "Il casco \u00e8 obbligatorio per i conducenti di motocicli non dotati di cellula di sicurezza e di dispositivi di ritenuta",
        "ans": true
    },
    {
        "image": null,
        "quiz": "Il casco \u00e8 obbligatorio per il passeggero di un motociclo privo di cellula di sicurezza e sistemi di ritenuta",
        "ans": true
    },
    {
        "image": null,
        "quiz": "Il casco non deve essere pulito con benzina",
        "ans": true
    },
    {
        "image": null,
        "quiz": "Il casco non deve essere pulito con solventi",
        "ans": true
    },
    {
        "image": null,
        "quiz": "Il casco non \u00e8 obbligatorio per i conducenti di ciclomotori a due ruote",
        "ans": false
    },
    {
        "image": null,
        "quiz": "Il casco subisce un processo di invecchiamento dovuto a luce e calore",
        "ans": true
    },
    {
        "image": null,
        "quiz": "Indossare il casco in modo errato o senza averlo correttamente allacciato pu\u00f2 comportare gravi rischi alla salute in caso di caduta o incidente",
        "ans": true
    },
    {
        "image": null,
        "quiz": "La calotta del casco pu\u00f2 essere riparata con nastro adesivo di tipo speciale, se presenta una rottura inferiore ai tre centimetri",
        "ans": false
    },
    {
        "image": null,
        "quiz": "La pulizia del casco deve essere effettuata con detersivi non corrosivi",
        "ans": true
    },
    {
        "image": null,
        "quiz": "La robustezza della calotta esterna del casco potrebbe essere compromessa da solventi presenti in vernici o colle",
        "ans": true
    },
    {
        "image": null,
        "quiz": "La visiera del casco deve essere sostituita se rigata o danneggiata",
        "ans": true
    },
    {
        "image": null,
        "quiz": "La visiera del casco deve garantire la perfetta visibilit\u00e0 con qualunque condizione di luce o illuminazione",
        "ans": true
    },
    {
        "image": null,
        "quiz": "La visiera del casco peggiora notevolmente la visibilit\u00e0 e quindi va usata il meno possibile",
        "ans": false
    },
    {
        "image": null,
        "quiz": "La visiera del casco pu\u00f2 essere riparata con nastro adesivo, purch\u00e9 sia di tipo ultra trasparente",
        "ans": false
    },
    {
        "image": null,
        "quiz": "Sul casco possono essere applicati adesivi di qualunque tipo, purch\u00e9 non coprano la visiera",
        "ans": false
    }
]